{
  "last_updated": "2025-11-29T08:01:46.540360",
  "tickets": {
    "Conway_538c3383": {
      "status": "Tramitada",
      "last_updated": "2025-11-29T08:01:46.540313",
      "ticket_id": "538c3383",
      "brand": "Conway",
      "email": "GARANTIAS@GUIJARROTOTESPORT.ES",
      "empresa": "GUIJARRO TOT ESPORT",
      "creation_date": "14/11/2025"
    },
    "Conway_8c43fd30": {
      "status": "Tramitada",
      "last_updated": "2025-11-29T08:01:46.540298",
      "ticket_id": "8c43fd30",
      "brand": "Conway",
      "email": "alcubikes@alcubikes.com",
      "empresa": "ALCUBIKES S.L.",
      "creation_date": "27/11/2025"
    },
    "Conway_c75ef1e3": {
      "status": "Tramitada",
      "last_updated": "2025-11-29T08:01:46.540308",
      "ticket_id": "c75ef1e3",
      "brand": "Conway",
      "email": "alcubikes@alcubikes.com",
      "empresa": "ALCUBIKES S.L.",
      "creation_date": "27/11/2025"
    }
  }
}